{"name":"overstorten","description":"overstortenview","requested":"2015-08-17T14:28:42.433Z","bounds":[[4.80617801177768,52.3283479518408],[4.9945987349629,52.4197266542279]],"status":"complete","resolution":33,"diskName":"overstorten","contaminatorSize":110,"log":[{"date":"2015-08-17T14:28:42.434Z","message":"added to queue"},{"date":"2015-08-17T14:28:42.799Z","message":"started generating"},{"date":"2015-08-17T14:29:04.105Z","message":"starting png writes"},{"date":"2015-08-17T14:29:25.463Z","message":"starting clippath write"},{"date":"2015-08-17T14:29:25.487Z","message":"starting fieldInfo write"},{"date":"2015-08-17T14:29:25.488Z","message":"completed"}],"variants":["wet"],"borderFalloffDistance":66}